portability/__init__.py
portability/ray_runner.py
ray_beam_runner/__init__.py
ray_beam_runner/collection.py
ray_beam_runner/custom_actor_pool.py
ray_beam_runner/overrides.py
ray_beam_runner/ray_runner.py
ray_beam_runner/ray_runner_test.py
ray_beam_runner/translator.py
ray_beam_runner/util.py
ray_beam_runner/portability/__init__.py
ray_beam_runner/portability/ray_runner.py
ray_beam-0.0.1.dist-info/LICENSE
ray_beam-0.0.1.dist-info/METADATA
ray_beam-0.0.1.dist-info/WHEEL
ray_beam-0.0.1.dist-info/top_level.txt
ray_beam-0.0.1.dist-info/RECORD
