Metadata-Version: 2.1
Name: ray-beam
Version: 0.0.1
Summary: A Ray runner for Apache Beam
Home-page: https://github.com/ray-project/ray_beam_runner
Author: Ray Team
Author-email: UNKNOWN
License: UNKNOWN
Platform: UNKNOWN
Requires-Dist: ray
Requires-Dist: apache-beam
